physense_emu/__init__.py
physense_emu-2.0.0.dist-info/LICENSE.txt
physense_emu-2.0.0.dist-info/METADATA
physense_emu-2.0.0.dist-info/WHEEL
physense_emu-2.0.0.dist-info/top_level.txt
physense_emu-2.0.0.dist-info/RECORD
