Metadata-Version: 2.1
Name: physense-emu
Version: 2.0.0
Summary: A sample Python project
Home-page: https://github.com/primeteacher/physense_emu
Author: Jason Silverstein
Author-email: jsilver5@dtcc.edu
License: UNKNOWN
Keywords: itn160
Platform: UNKNOWN
Classifier: Development Status :: 3 - Alpha
Classifier: Topic :: Software Development :: Build Tools
Classifier: License :: OSI Approved :: MIT License
Classifier: Programming Language :: Python :: 3
Requires-Dist: physense-sim
